cryptarchive/constants.py
cryptarchive/client.py
cryptarchive/icryptarchive.py
cryptarchive/server.py
cryptarchive/errors.py
cryptarchive/usermanager.py
cryptarchive/socketclient.py
cryptarchive/index.py
cryptarchive/runner.py
cryptarchive/reconstruct.py
cryptarchive/challenge.py
cryptarchive/__init__.py
cryptarchive-0.1.6.dist-info/metadata.json
cryptarchive-0.1.6.dist-info/entry_points.txt
cryptarchive-0.1.6.dist-info/DESCRIPTION.rst
cryptarchive-0.1.6.dist-info/WHEEL
cryptarchive-0.1.6.dist-info/METADATA
cryptarchive-0.1.6.dist-info/top_level.txt
cryptarchive-0.1.6.dist-info/RECORD
