Metadata-Version: 2.0
Name: cryptarchive
Version: 0.1.6
Summary: encrypted storage server and client
Home-page: https://github.com/bennr01/cryptarchive/
Author: bennr01
Author-email: benjamin99.vogt@web.de
License: AGPLv3
Keywords: crypto server data storage network CLI
Platform: UNKNOWN
Classifier: License :: OSI Approved :: GNU Affero General Public License v3
Classifier: Topic :: Security :: Cryptography
Classifier: Programming Language :: Python
Classifier: Development Status :: 3 - Alpha
Classifier: Programming Language :: Python :: 2.6
Classifier: Programming Language :: Python :: 2.7
Requires-Dist: twisted
Requires-Dist: pycryptodome
Requires-Dist: zope.interface
